packaging/__init__.py
packaging/flight_path.py
usra_pomona_flightpath-0.0.1.dist-info/LICENSE.txt
usra_pomona_flightpath-0.0.1.dist-info/METADATA
usra_pomona_flightpath-0.0.1.dist-info/WHEEL
usra_pomona_flightpath-0.0.1.dist-info/top_level.txt
usra_pomona_flightpath-0.0.1.dist-info/RECORD
